jaxus/__init__.py
jaxus/beamforming/__init__.py
jaxus/beamforming/beamform.py
jaxus/beamforming/delay_multiply_and_sum.py
jaxus/beamforming/lens_correction.py
jaxus/beamforming/minimum_variance.py
jaxus/beamforming/pixelgrid.py
jaxus/containers/__init__.py
jaxus/containers/medium.py
jaxus/containers/probe.py
jaxus/containers/receive.py
jaxus/containers/transmit.py
jaxus/containers/waveform.py
jaxus/convenience.py
jaxus/data/__init__.py
jaxus/data/hdf5_data_format.py
jaxus/data/verasonics.py
jaxus/metrics/__init__.py
jaxus/metrics/gcnr.py
jaxus/plotting.py
jaxus/rf_simulator.py
jaxus/styles/darkmode.mplstyle
jaxus/styles/lightmode.mplstyle
jaxus/utils/__init__.py
jaxus/utils/checks.py
jaxus/utils/log.py
jaxus/utils/testing.py
jaxus-0.2.1.dist-info/LICENSE.txt
jaxus-0.2.1.dist-info/METADATA
jaxus-0.2.1.dist-info/WHEEL
jaxus-0.2.1.dist-info/RECORD
