Metadata-Version: 2.1
Name: jaxus
Version: 0.2.1
Summary: Basic ultrasound simulation and reconstruction functionality implemented in JAX.
License: MIT
Author: Vincent van de Schaft
Requires-Python: >=3.10,<4.0
Classifier: License :: OSI Approved :: MIT License
Classifier: Programming Language :: Python :: 3
Classifier: Programming Language :: Python :: 3.10
Classifier: Programming Language :: Python :: 3.11
Classifier: Programming Language :: Python :: 3.12
Requires-Dist: h5py
Requires-Dist: matplotlib
Requires-Dist: numpy
Requires-Dist: tqdm
